credential/__init__.py
credential/credential.py
searchconsole/__init__.py
searchconsole/searchconsole.py
pysearchconsole-1.0.5.dist-info/METADATA
pysearchconsole-1.0.5.dist-info/WHEEL
pysearchconsole-1.0.5.dist-info/top_level.txt
pysearchconsole-1.0.5.dist-info/RECORD
