Metadata-Version: 2.1
Name: pysearchconsole
Version: 1.0.5
Summary: PySearchConsole is a Python library that  allows you to get query and analyze data from your website's Search Console account, including search analytics, crawl errors, sitemaps, and more.
Home-page: https://github.com/Rahulkatoch99/py_searchconsole
Author: Rahul Katoch, Harish kumar
Author-email: rahulkatoch99@gmail.com
Maintainer-email: rahulkatoch99@gmail.com, echkayweb@gmail.com
License: MIT
Keywords: search console api google seo python libraries API integration web traffic analysis
Classifier: Development Status :: 5 - Production/Stable
Classifier: Intended Audience :: Developers
Classifier: License :: OSI Approved :: MIT License
Classifier: Programming Language :: Python :: 3
Classifier: Programming Language :: Python :: 3.6
Classifier: Programming Language :: Python :: 3.7
Classifier: Programming Language :: Python :: 3.8
Classifier: Programming Language :: Python :: 3.9
Classifier: Programming Language :: Python :: 3.10
Requires-Python: >=3.6
Requires-Dist: google-api-python-client
Requires-Dist: httplib2
Requires-Dist: oauth2client
